pdocr_rpc/__init__.py
pdocr_rpc/__version__.py
pdocr_rpc/conf.py
pdocr_rpc/server.py
pdocr_rpc-2024.5.28.dist-info/METADATA
pdocr_rpc-2024.5.28.dist-info/WHEEL
pdocr_rpc-2024.5.28.dist-info/licenses/LICENSE
pdocr_rpc-2024.5.28.dist-info/licenses/NOTICE
pdocr_rpc-2024.5.28.dist-info/RECORD
