Metadata-Version: 2.1
Name: pdocr-rpc
Version: 2024.5.28
Summary: PaddleOCR-RPC
Project-URL: Source, https://github.com/linuxdeepin/pdocr-rpc
Project-URL: Documentation, https://linuxdeepin.github.io/pdocr-rpc
Author-email: mikigo <1964191531@qq.com>
License-File: LICENSE
License-File: NOTICE
Classifier: License :: OSI Approved :: Apache Software License
Classifier: Operating System :: OS Independent
Classifier: Programming Language :: Python :: 3
Requires-Python: >=3.6
Requires-Dist: funnylog
Requires-Dist: pillow; sys_platform == 'win32'
Requires-Dist: pyscreenshot; sys_platform == 'linux'
Provides-Extra: doc
Requires-Dist: mkdocs-material; extra == 'doc'
Provides-Extra: server
Requires-Dist: paddleocr>=2.0.1; extra == 'server'
Requires-Dist: paddlepaddle; extra == 'server'
Provides-Extra: test
Requires-Dist: pytest; extra == 'test'
